get_folder_structure/__init__.py
get_folder_structure/main.py
get_folder_structure-0.1.9.dist-info/entry_points.txt
get_folder_structure-0.1.9.dist-info/METADATA
get_folder_structure-0.1.9.dist-info/WHEEL
get_folder_structure-0.1.9.dist-info/RECORD
