Metadata-Version: 2.3
Name: get-folder-structure
Version: 0.1.9
Summary: 
Author: jaytrairat
Author-email: jay.trairat@gmail.com
Requires-Python: >=3.13
Classifier: Programming Language :: Python :: 3
Classifier: Programming Language :: Python :: 3.13
Requires-Dist: openpyxl (>=3.1.5,<4.0.0)
